pydatafs/__init__.py
pydatafs/errors.py
pydatafs/files.py
pydatafs/filesystem.py
pydatafs/handle.py
pydatafs-0.1.0.dist-info/LICENSE
pydatafs-0.1.0.dist-info/METADATA
pydatafs-0.1.0.dist-info/WHEEL
pydatafs-0.1.0.dist-info/top_level.txt
pydatafs-0.1.0.dist-info/RECORD
