Metadata-Version: 2.1
Name: pydatafs
Version: 0.1.0
Summary: Library for pythonically constructing fuse filesystems
Author-email: Audrey Dutcher <audrey@rhelmot.io>
License: Copyright 2023 Audrey Dutcher
Requires-Python: >=3.8
License-File: LICENSE
Requires-Dist: pyfuse3
Provides-Extra: dev
Requires-Dist: tox (>=4.0.0) ; extra == 'dev'
Requires-Dist: black ; extra == 'dev'
Requires-Dist: isort ; extra == 'dev'
Requires-Dist: pre-commit ; extra == 'dev'
Provides-Extra: doc
Requires-Dist: sphinx ; extra == 'doc'
Requires-Dist: furo ; extra == 'doc'
Provides-Extra: lint
Requires-Dist: pylint ; extra == 'lint'
Provides-Extra: test
Requires-Dist: pytest ; extra == 'test'
Requires-Dist: pytest-cov ; extra == 'test'
Requires-Dist: coverage[toml] ; extra == 'test'
Provides-Extra: type
Requires-Dist: mypy ; extra == 'type'
